{
  "BACKGROUND": "0x71",
  "MENU_NORMAL_TEXT": "0x70",
  "MENU_DISABLED_TEXT": "0x78",
  "MENU_SHORTCUT_TEXT": "0x74",
  "MENU_NORMAL_SELECTION": "0x20",
  "MENU_DISABLED_SELECTION": "0x28",
  "MENU_SHORTCUT_SELECTION": "0x24",
  "BLUE_WINDOW_FRAME_PASSIVE": "0x17",
  "BLUE_WINDOW_FRAME_ACTIVE": "0x1F",
  "BLUE_WINDOW_FRAME_ICON": "0x1A",
  "BLUE_WINDOW_SCROLLBAR_PAGE": "0x31",
  "BLUE_WINDOW_SCROLLBAR_CONTROLS": "0x31",
  "BLUE_WINDOW_SCROLLER_NORMAL": "0x78",
  "BLUE_WINDOW_SCROLLER_SELECTED": "0x7F",
  "BLUE_WINDOW_RESERVED": "0x1F",
  "CYAN_WINDOW_FRAME_PASSIVE": "0x31",
  "CYAN_WINDOW_FRAME_ACTIVE": "0x3F",
  "CYAN_WINDOW_FRAME_ICON": "0x3A",
  "CYAN_WINDOW_SCROLLBAR_PAGE": "0x13",
  "CYAN_WINDOW_SCROLLBAR_CONTROLS": "0x13",
  "CYAN_WINDOW_SCROLLER_NORMAL": "0x3E",
  "CYAN_WINDOW_SCROLLER_SELECTED": "0x21",
  "CYAN_WINDOW_RESERVED": "0x3F",
  "GRAY_WINDOW_FRAME_PASSIVE": "0x70",
  "GRAY_WINDOW_FRAME_ACTIVE": "0x7F",
  "GRAY_WINDOW_FRAME_ICON": "0x7A",
  "GRAY_WINDOW_SCROLLBAR_PAGE": "0x13",
  "GRAY_WINDOW_SCROLLBAR_CONTROLS": "0x13",
  "GRAY_WINDOW_SCROLLER_NORMAL": "0x70",
  "GRAY_WINDOW_SCROLLER_SELECTED": "0x7F",
  "GRAY_WINDOW_RESERVED": "0x7E",
  "GRAY_DIALOG_FRAME_PASSIVE": "0x70",
  "GRAY_DIALOG_FRAME_ACTIVE": "0x7F",
  "GRAY_DIALOG_FRAME_ICON": "0x7A",
  "GRAY_DIALOG_SCROLLBAR_PAGE": "0x13",
  "GRAY_DIALOG_SCROLLBAR_CONTROLS": "0x13",
  "GRAY_DIALOG_STATIC_TEXT": "0x70",
  "GRAY_DIALOG_LABEL_NORMAL": "0x70",
  "GRAY_DIALOG_LABEL_SELECTED": "0x7F",
  "GRAY_DIALOG_LABEL_SHORTCUT": "0x7E",
  "GRAY_DIALOG_BUTTON_NORMAL": "0x8F",
  "GRAY_DIALOG_BUTTON_DEFAULT": "0x8B",
  "GRAY_DIALOG_BUTTON_SELECTED": "0x9F",
  "GRAY_DIALOG_BUTTON_DISABLED": "0x78",
  "GRAY_DIALOG_BUTTON_SHORTCUT": "0x8E",
  "GRAY_DIALOG_BUTTON_SHADOW": "0x70",
  "GRAY_DIALOG_CLUSTER_NORMAL": "0x78",
  "GRAY_DIALOG_CLUSTER_SELECTED": "0x7F",
  "GRAY_DIALOG_CLUSTER_SHORTCUT": "0x7E",
  "GRAY_DIALOG_INPUT_LINE_NORMAL_TEXT": "0x0F",
  "GRAY_DIALOG_INPUT_LINE_SELECTED_TEXT": "0x9F",
  "GRAY_DIALOG_INPUT_LINE_ARROWS": "0x0E",
  "GRAY_DIALOG_HISTORY_ARROW": "0x9F",
  "GRAY_DIALOG_HISTORY_SIDES": "0x79",
  "GRAY_DIALOG_HISTORY_WINDOW_PAGE": "0x31",
  "GRAY_DIALOG_HISTORY_WINDOW_CONTROLS": "0x31",
  "GRAY_DIALOG_LIST_VIEWER_NORMAL": "0x30",
  "GRAY_DIALOG_LIST_VIEWER_FOCUSED": "0x0F",
  "GRAY_DIALOG_LIST_VIEWER_SELECTED": "0x3F",
  "GRAY_DIALOG_LIST_VIEWER_DIVIDER": "0x31",
  "GRAY_DIALOG_INFO_PANE": "0x8F",
  "GRAY_DIALOG_CLUSTER_DISABLED": "0x30",
  "GRAY_DIALOG_RESERVED": "0x3E",
  "EDITOR_COLOR_064": "0x30",
  "EDITOR_COLOR_065": "0x38",
  "EDITOR_COLOR_066": "0x3E",
  "EDITOR_COLOR_067": "0x0F",
  "EDITOR_COLOR_068": "0x07",
  "EDITOR_COLOR_069": "0x0E",
  "EDITOR_COLOR_070": "0x87",
  "EDITOR_COLOR_071": "0x8F",
  "EDITOR_COLOR_072": "0x8F",
  "EDITOR_COLOR_073": "0x8B",
  "EDITOR_COLOR_074": "0x8F",
  "EDITOR_COLOR_075": "0xF0",
  "EDITOR_COLOR_076": "0x87",
  "EDITOR_COLOR_077": "0x7F",
  "EDITOR_COLOR_078": "0x1C",
  "EDITOR_COLOR_079": "0x00",
  "BLUE_DIALOG_CLUSTER_SELECTED": "0x87",
  "BLUE_DIALOG_CLUSTER_SHORTCUT": "0x8F",
  "BLUE_DIALOG_INPUT_LINE_NORMAL_TEXT": "0x8B",
  "BLUE_DIALOG_INPUT_LINE_SELECTED_TEXT": "0x8F",
  "BLUE_DIALOG_INPUT_LINE_ARROWS": "0xF0",
  "BLUE_DIALOG_HISTORY_ARROW": "0x87",
  "BLUE_DIALOG_HISTORY_SIDES": "0x8F",
  "BLUE_DIALOG_HISTORY_WINDOW_PAGE": "0x8E",
  "BLUE_DIALOG_HISTORY_WINDOW_CONTROLS": "0x30",
  "BLUE_DIALOG_LIST_VIEWER_NORMAL": "0x3E",
  "BLUE_DIALOG_LIST_VIEWER_FOCUSED": "0x3F",
  "BLUE_DIALOG_LIST_VIEWER_SELECTED": "0x8F",
  "BLUE_DIALOG_LIST_VIEWER_DIVIDER": "0x87",
  "BLUE_DIALOG_INFO_PANE": "0x70",
  "BLUE_DIALOG_CLUSTER_DISABLED": "0x87",
  "BLUE_DIALOG_RESERVED": "0x8F",
  "CYAN_DIALOG_FRAME_PASSIVE": "0x3F",
  "CYAN_DIALOG_FRAME_ACTIVE": "0x8F",
  "CYAN_DIALOG_FRAME_ICON": "0x3F",
  "CYAN_DIALOG_SCROLLBAR_PAGE": "0x8E",
  "CYAN_DIALOG_SCROLLBAR_CONTROLS": "0x8E",
  "CYAN_DIALOG_STATIC_TEXT": "0x70",
  "CYAN_DIALOG_LABEL_NORMAL": "0x8B",
  "CYAN_DIALOG_LABEL_SELECTED": "0x87",
  "CYAN_DIALOG_LABEL_SHORTCUT": "0x30",
  "CYAN_DIALOG_BUTTON_NORMAL": "0x3F",
  "CYAN_DIALOG_BUTTON_DEFAULT": "0x0F",
  "CYAN_DIALOG_BUTTON_SELECTED": "0x3E",
  "CYAN_DIALOG_BUTTON_DISABLED": "0x0E",
  "CYAN_DIALOG_BUTTON_SHORTCUT": "0x31",
  "CYAN_DIALOG_BUTTON_SHADOW": "0x31",
  "CYAN_DIALOG_CLUSTER_NORMAL": "0x00",
  "CYAN_DIALOG_CLUSTER_SELECTED": "0x87",
  "CYAN_DIALOG_CLUSTER_SHORTCUT": "0x8F",
  "CYAN_DIALOG_INPUT_LINE_NORMAL_TEXT": "0x8B",
  "CYAN_DIALOG_INPUT_LINE_SELECTED_TEXT": "0x8F",
  "CYAN_DIALOG_INPUT_LINE_ARROWS": "0xF0",
  "CYAN_DIALOG_HISTORY_ARROW": "0x87",
  "CYAN_DIALOG_HISTORY_SIDES": "0x70",
  "FILE_INFO_COLOR_119": "0x8B",
  "FILE_INFO_COLOR_120": "0x8E",
  "FILE_INFO_COLOR_121": "0x8F",
  "FILE_INFO_COLOR_122": "0x87",
  "FILE_INFO_COLOR_123": "0x8F",
  "FILE_INFO_COLOR_124": "0x87",
  "FILE_INFO_COLOR_125": "0x8F",
  "FILE_FIND_COLOR_126": "0x70",
  "FILE_FIND_COLOR_127": "0x7F",
  "FILE_FIND_COLOR_128": "0x7A",
  "FILE_FIND_COLOR_129": "0x13",
  "FILE_FIND_COLOR_130": "0x13",
  "FILE_FIND_COLOR_131": "0x70",
  "FILE_FIND_COLOR_132": "0x30",
  "FILE_FIND_COLOR_133": "0x79",
  "FILE_FIND_COLOR_134": "0x39",
  "FILE_FIND_COLOR_135": "0x7E",
  "FILE_FIND_COLOR_136": "0x7E",
  "FILE_FIND_COLOR_137": "0x7F",
  "FILE_FIND_COLOR_138": "0x70",
  "DN_EXTRA_139": "0x37",
  "HELP_WINDOW_SLOT_002": "0x3F",
  "HELP_WINDOW_SLOT_003": "0x3A",
  "DN_EXTRA_142": "0x13",
  "DN_EXTRA_143": "0x13",
  "HELP_WINDOW_SLOT_006": "0x30",
  "HELP_WINDOW_SLOT_007": "0x3E",
  "HELP_WINDOW_SLOT_008": "0x1E",
  "FIXER_WINDOW_SLOT_002": "0x30",
  "FIXER_WINDOW_SLOT_003": "0x38",
  "FIXER_WINDOW_SLOT_004": "0x3E",
  "FIXER_WINDOW_SLOT_005": "0x0F",
  "FIXER_WINDOW_SLOT_006": "0x07",
  "FIXER_WINDOW_SLOT_007": "0x0E",
  "FIXER_WINDOW_SLOT_001": "0x87",
  "FIXER_WINDOW_SLOT_008": "0x8F",
  "FIXER_WINDOW_SLOT_009": "0x8F",
  "FIXER_WINDOW_SLOT_010": "0x8B",
  "FIXER_WINDOW_SLOT_011": "0x8F",
  "FIXER_WINDOW_SLOT_012": "0xF0",
  "FIXER_WINDOW_SLOT_013": "0x87",
  "FIXER_WINDOW_SLOT_014": "0x70",
  "FIXER_WINDOW_SLOT_015": "0x8E",
  "FIXER_WINDOW_SLOT_016": "0x30",
  "HELP_WINDOW_SLOT_009": "0x3F",
  "UNI_WINDOW_SLOT_016": "0x83",
  "DOUBLE_WINDOW_SLOT_032": "0x8E",
  "DB_WINDOW_SLOT_001": "0x38",
  "DB_WINDOW_SLOT_002": "0x3F",
  "DB_WINDOW_SLOT_003": "0x3A",
  "DB_WINDOW_SLOT_004": "0x31",
  "DB_WINDOW_SLOT_005": "0x3F",
  "DB_WINDOW_SLOT_006": "0x70",
  "DOUBLE_WINDOW_SLOT_033": "0x8F",
  "DOUBLE_WINDOW_SLOT_034": "0x8B",
  "DOUBLE_WINDOW_SLOT_035": "0x8A",
  "DOUBLE_WINDOW_SLOT_036": "0x83",
  "DOUBLE_WINDOW_SLOT_037": "0x82",
  "DOUBLE_WINDOW_SLOT_038": "0x8D",
  "GRAY_DIALOG_SLOT_033": "0x9E",
  "GRAY_DIALOG_SLOT_034": "0x8E",
  "DOUBLE_WINDOW_SLOT_039": "0x8C",
  "DOUBLE_WINDOW_SLOT_040": "0x89",
  "UNI_WINDOW_SLOT_017": "0x07",
  "UNI_WINDOW_SLOT_018": "0x7F",
  "UNI_WINDOW_SLOT_019": "0x03",
  "UNI_WINDOW_SLOT_020": "0x0F",
  "DOUBLE_WINDOW_SLOT_041": "0x8F",
  "DOUBLE_WINDOW_SLOT_042": "0x8F",
  "DOUBLE_WINDOW_SLOT_043": "0x8E",
  "UNI_WINDOW_SLOT_021": "0x8F",
  "UNI_WINDOW_SLOT_022": "0x8D",
  "UNI_WINDOW_SLOT_023": "0x8B",
  "DN_EXTRA_192": "0x70",
  "DN_EXTRA_193": "0x07",
  "DN_EXTRA_194": "0x3F",
  "DN_EXTRA_195": "0x3F",
  "DN_EXTRA_196": "0x3F",
  "DN_EXTRA_197": "0x3F",
  "DN_EXTRA_198": "0x3F",
  "DN_EXTRA_199": "0x3F",
  "DN_EXTRA_200": "0x3F",
  "DN_EXTRA_201": "0x3F",
  "DN_EXTRA_202": "0x3F",
  "DN_EXTRA_203": "0x3F",
  "DN_EXTRA_204": "0x3F",
  "DN_EXTRA_205": "0x3F",
  "DN_EXTRA_206": "0x3F",
  "DN_EXTRA_207": "0x3F",
  "DN_EXTRA_208": "0x3F",
  "DN_EXTRA_209": "0x3F",
  "DN_EXTRA_210": "0x3F",
  "DN_EXTRA_211": "0x3F",
  "DN_EXTRA_212": "0x3F",
  "DN_EXTRA_213": "0x3F",
  "DN_EXTRA_214": "0x3F",
  "DN_EXTRA_215": "0x3F",
  "DN_EXTRA_216": "0x3F",
  "DN_EXTRA_217": "0x3F",
  "DN_EXTRA_218": "0x3F",
  "DN_EXTRA_219": "0x3F",
  "DN_EXTRA_220": "0x3F",
  "DN_EXTRA_221": "0x3F",
  "DN_EXTRA_222": "0x3F",
  "DN_EXTRA_223": "0x3F",
  "DN_EXTRA_224": "0x08",
  "DN_EXTRA_225": "0xCF",
  "DN_EXTRA_226": "0xCE",
  "DN_EXTRA_227": "0x0F",
  "DN_EXTRA_228": "0x0E"
}
